iso2mesh/__init__.py
iso2mesh/brain2mesh.py
iso2mesh/core.py
iso2mesh/geometry.py
iso2mesh/io.py
iso2mesh/line.py
iso2mesh/modify.py
iso2mesh/plot.py
iso2mesh/raster.py
iso2mesh/register.py
iso2mesh/surf.py
iso2mesh/trait.py
iso2mesh/utils.py
iso2mesh/volume.py
iso2mesh-0.5.4.dist-info/licenses/LICENSE
iso2mesh-0.5.4.dist-info/METADATA
iso2mesh-0.5.4.dist-info/WHEEL
iso2mesh-0.5.4.dist-info/top_level.txt
iso2mesh-0.5.4.dist-info/RECORD
