Metadata-Version: 2.4
Name: iso2mesh
Version: 0.5.4
Summary: One-liner 3D Surface and Tetrahedral Mesh Generation Toolbox
Home-page: https://github.com/NeuroJSON/pyiso2mesh
Author: Qianqian Fang
Author-email: fangqq@gmail.com
Maintainer: Qianqian Fang
License: GPLv3+
Keywords: Iso2Mesh,Brain2Mesh,JSONLab,EasyH5,Mesh generation,Finite element method,FEM,FEA,MATLAB,Mesh-based Monte Carlo,CGAL,Tetgen,CSG,Boolean,Surface mesh,Tetrahedral mesh,Modeling,Multiphysics,Image processing,NeuroJSON,Binary JSON,JSON,Data format
Platform: any
Classifier: Development Status :: 4 - Beta
Classifier: Intended Audience :: Developers
Classifier: Topic :: Software Development :: Build Tools
Classifier: License :: OSI Approved :: GNU General Public License v3 or later (GPLv3+)
Classifier: Programming Language :: Python :: 3
Classifier: Programming Language :: Python :: 3.4
Classifier: Programming Language :: Python :: 3.5
Classifier: Programming Language :: Python :: 3.6
Classifier: Programming Language :: Python :: 3.7
Classifier: Programming Language :: Python :: 3.8
Classifier: Programming Language :: Python :: 3.9
Classifier: Programming Language :: Python :: 3.10
Classifier: Programming Language :: Python :: 3.11
Classifier: Programming Language :: Python :: 3.12
Classifier: Programming Language :: Python :: 3.13
Classifier: Topic :: Software Development :: Libraries
Classifier: Topic :: Software Development :: Libraries :: Python Modules
License-File: LICENSE
Requires-Dist: numpy>=1.8.0
Requires-Dist: matplotlib
Requires-Dist: jdata>=0.8.2
Requires-Dist: bjdata
Dynamic: author
Dynamic: author-email
Dynamic: classifier
Dynamic: description
Dynamic: description-content-type
Dynamic: home-page
Dynamic: keywords
Dynamic: license
Dynamic: license-file
Dynamic: maintainer
Dynamic: platform
Dynamic: requires-dist
Dynamic: summary
